qBitrr/__init__.py
qBitrr/arss.py
qBitrr/auto_update.py
qBitrr/bundled_data.py
qBitrr/config.py
qBitrr/config_version.py
qBitrr/db_lock.py
qBitrr/db_recovery.py
qBitrr/env_config.py
qBitrr/errors.py
qBitrr/ffprobe.py
qBitrr/gen_config.py
qBitrr/home_path.py
qBitrr/logger.py
qBitrr/main.py
qBitrr/search_activity_store.py
qBitrr/tables.py
qBitrr/utils.py
qBitrr/versioning.py
qBitrr/webui.py
qBitrr/static/favicon-16x16.png
qBitrr/static/favicon-32x32.png
qBitrr/static/favicon-48x48.png
qBitrr/static/favicon.ico
qBitrr/static/icon-192.png
qBitrr/static/icon-512.png
qBitrr/static/index.html
qBitrr/static/logov2-clean.png
qBitrr/static/logov2-clean.svg
qBitrr/static/manifest.json
qBitrr/static/sw.js
qBitrr/static/vite.svg
qBitrr/static/assets/ArrView.js
qBitrr/static/assets/ArrView.js.map
qBitrr/static/assets/ConfigView.js
qBitrr/static/assets/ConfigView.js.map
qBitrr/static/assets/LogsView.js
qBitrr/static/assets/LogsView.js.map
qBitrr/static/assets/ProcessesView.js
qBitrr/static/assets/ProcessesView.js.map
qBitrr/static/assets/app.css
qBitrr/static/assets/app.js
qBitrr/static/assets/app.js.map
qBitrr/static/assets/build.svg
qBitrr/static/assets/check-mark.svg
qBitrr/static/assets/close.svg
qBitrr/static/assets/download.svg
qBitrr/static/assets/gear.svg
qBitrr/static/assets/lidarr.svg
qBitrr/static/assets/live-streaming.svg
qBitrr/static/assets/log.svg
qBitrr/static/assets/logo.svg
qBitrr/static/assets/plus.svg
qBitrr/static/assets/process.svg
qBitrr/static/assets/react-select.esm.js
qBitrr/static/assets/react-select.esm.js.map
qBitrr/static/assets/refresh-arrow.svg
qBitrr/static/assets/table.js
qBitrr/static/assets/table.js.map
qBitrr/static/assets/trash.svg
qBitrr/static/assets/up-arrow.svg
qBitrr/static/assets/useInterval.js
qBitrr/static/assets/useInterval.js.map
qBitrr/static/assets/vendor.js
qBitrr/static/assets/vendor.js.map
qBitrr/static/assets/visibility.svg
qbitrr2-5.6.2.dist-info/licenses/LICENSE
qbitrr2-5.6.2.dist-info/METADATA
qbitrr2-5.6.2.dist-info/WHEEL
qbitrr2-5.6.2.dist-info/entry_points.txt
qbitrr2-5.6.2.dist-info/top_level.txt
qbitrr2-5.6.2.dist-info/RECORD
